src/__init__.py
src/misc_utils.py
miscelltools-0.0.2.dist-info/LICENSE.txt
miscelltools-0.0.2.dist-info/METADATA
miscelltools-0.0.2.dist-info/WHEEL
miscelltools-0.0.2.dist-info/top_level.txt
miscelltools-0.0.2.dist-info/RECORD
