Metadata-Version: 2.1
Name: miscelltools
Version: 0.0.2
Summary: Toolkit containing different 
Home-page: 
Author: Yasser Alemán-Gómez
Author-email: yasseraleman@gmail.com
License: Apache version 2.0
Keywords: parcellation
Classifier: Development Status :: 5 - Production/Stable
Classifier: Intended Audience :: Education
Classifier: Operating System :: POSIX :: Linux
Classifier: License :: OSI Approved :: Apache Software License
Classifier: Programming Language :: Python :: 3
License-File: LICENSE.txt
Requires-Dist: numpy
